flask_uauth/__init__.py
flask_uauth/decorators.py
flask_uauth/mixins.py
flask_uauth/proxies.py
flask_uauth/uauth.py
flask_uauth-0.2.0.dist-info/LICENSE
flask_uauth-0.2.0.dist-info/METADATA
flask_uauth-0.2.0.dist-info/WHEEL
flask_uauth-0.2.0.dist-info/top_level.txt
flask_uauth-0.2.0.dist-info/zip-safe
flask_uauth-0.2.0.dist-info/RECORD
