Metadata-Version: 2.1
Name: flask-uauth
Version: 0.2.0
Summary: Simple authentication for Flask REST apis
Home-page: https://github.com/pmatigakis/flask-uauth
Author: Panagiotis Matigakis
Author-email: pmatigakis@gmail.com
License: UNKNOWN
Platform: UNKNOWN
Classifier: Development Status :: 3 - Alpha
Classifier: Intended Audience :: Developers
Classifier: Natural Language :: English
Classifier: Programming Language :: Python :: 3
Classifier: Programming Language :: Python :: 3.6
Classifier: Programming Language :: Python :: 3.7
Classifier: Programming Language :: Python :: 3.8
Classifier: Programming Language :: Python :: Implementation :: CPython
Classifier: License :: OSI Approved :: MIT License
Classifier: Operating System :: OS Independent
Requires-Dist: Flask (>=1.0)
